ChangeLog.txt
LICENSE.txt
MANIFEST.in
README.rst
setup.py
dexml/__init__.py
dexml/fields.py
dexml/test.py
dexml.egg-info/PKG-INFO
dexml.egg-info/SOURCES.txt
dexml.egg-info/dependency_links.txt
dexml.egg-info/top_level.txt